star_ray_xml/__init__.py
star_ray_xml/_element.py
star_ray_xml/ambient.py
star_ray_xml/query.py
star_ray_xml/sensor.py
star_ray_xml/state.py
star_ray_xml/utils/__init__.py
star_ray_xml/utils/_utils.py
star_ray_xml-0.0.6.dist-info/LICENSE
star_ray_xml-0.0.6.dist-info/METADATA
star_ray_xml-0.0.6.dist-info/WHEEL
star_ray_xml-0.0.6.dist-info/top_level.txt
star_ray_xml-0.0.6.dist-info/RECORD
