Metadata-Version: 2.1
Name: star_ray_xml
Version: 0.0.6
Summary: An extension to the star_ray platform that uses XML as a description language for the state of an environment.
Author-email: Benedict Wilkins <benrjw@gmail.com>
License: GNU GENERAL PUBLIC LICENSE
Project-URL: Repository, https://github.com/dicelab-rhul/star-ray-xml
Requires-Python: >=3.10
License-File: LICENSE
Requires-Dist: star-ray>=0.0.7
Requires-Dist: lxml>=5.2.2
Requires-Dist: pydantic>=2.8.2
